revisitpy_server/__init__.py
revisitpy_server/run_server.py
revisitpy_server/server.py
revisitpy_server/static/404.html
revisitpy_server/static/README.md
revisitpy_server/static/global.json
revisitpy_server/static/index.html
revisitpy_server/static/vite.svg
revisitpy_server/static/assets/VLAT1-vnvZ7yRm.png
revisitpy_server/static/assets/VLAT10-BMGl61Mu.png
revisitpy_server/static/assets/VLAT11-Bxb0LCYD.png
revisitpy_server/static/assets/VLAT12-Ch9t16aS.png
revisitpy_server/static/assets/VLAT2-Ck6767Xc.png
revisitpy_server/static/assets/VLAT3-Cwe4YjoY.png
revisitpy_server/static/assets/VLAT4-CZ1oExNp.png
revisitpy_server/static/assets/VLAT5-C6h4Z1Dz.png
revisitpy_server/static/assets/VLAT6-BSRlVaih.png
revisitpy_server/static/assets/VLAT7-BF4fuAsD.png
revisitpy_server/static/assets/VLAT8-Cf_OYzE7.png
revisitpy_server/static/assets/VLAT9-CkTk-Ex0.png
revisitpy_server/static/assets/costco_card-B3j7PHjO.png
revisitpy_server/static/assets/index-sJszxEMG.js
revisitpy_server/static/assets/index-sy4LQ6le.css
revisitpy_server/static/demo-click-accuracy-test/config.json
revisitpy_server/static/demo-click-accuracy-test/assets/help.md
revisitpy_server/static/demo-click-accuracy-test/assets/introduction.md
revisitpy_server/static/demo-dynamic/config.json
revisitpy_server/static/demo-dynamic/assets/help.md
revisitpy_server/static/demo-dynamic/assets/introduction.md
revisitpy_server/static/demo-html/config.json
revisitpy_server/static/demo-html/assets/bar-chart.html
revisitpy_server/static/demo-html/assets/help.md
revisitpy_server/static/demo-html/assets/introduction.md
revisitpy_server/static/demo-html-input/config.json
revisitpy_server/static/demo-html-input/assets/bar-chart-interaction.html
revisitpy_server/static/demo-html-input/assets/help.md
revisitpy_server/static/demo-html-input/assets/introduction.md
revisitpy_server/static/demo-html-trrack/config.json
revisitpy_server/static/demo-html-trrack/assets/dots-count.html
revisitpy_server/static/demo-html-trrack/assets/help.md
revisitpy_server-1.13.0.dist-info/METADATA
revisitpy_server-1.13.0.dist-info/WHEEL
revisitpy_server-1.13.0.dist-info/licenses/LICENSE
revisitpy_server-1.13.0.dist-info/RECORD
