Metadata-Version: 2.4
Name: revisitpy_server
Version: 1.13.0
License-File: LICENSE
